{"assets":{"AdobeStock_266739495.mov-0.0000-18.3877":{"type":"video","index":0,"url":{"web":"assets\/AdobeStock_266739495.mov-0.0000-18.3877.mov","native":"assets\/AdobeStock_266739495.mov-0.0000-18.3877.mov"},"width":1920,"height":1080},"4DCB6BA1E98373574D43AEEA1A1006BB":{"type":"texture","index":6,"url":{"native":"assets\/5BE811FD-EF1B-4AAF-A494-4BCAB0D96B98.pdf"},"width":448,"height":23},"0B143BA6911C8E83FB8E8707BC7A323C":{"type":"texture","index":4,"url":{"native":"assets\/5BE811FD-EF1B-4AAF-A494-4BCAB0D96B98.pdf"},"width":382,"height":103},"C25C25FF361FB24FC35F6B120D2F252D":{"type":"texture","index":0,"url":{"native":"assets\/5BE811FD-EF1B-4AAF-A494-4BCAB0D96B98.pdf"},"width":1920,"height":1080},"05FF591A24F0531751D2F3C5FC5C4823":{"type":"texture","index":3,"url":{"native":"assets\/5BE811FD-EF1B-4AAF-A494-4BCAB0D96B98.pdf"},"width":1936,"height":295},"5E5E1E95F6034F4F396B66AE5DC1F5A8":{"type":"texture","index":2,"url":{"native":"assets\/5BE811FD-EF1B-4AAF-A494-4BCAB0D96B98.pdf"},"width":78,"height":368},"0FE07C9B32DA6205569FAD6450FF1E81":{"type":"texture","index":5,"url":{"native":"assets\/5BE811FD-EF1B-4AAF-A494-4BCAB0D96B98.pdf"},"width":1223,"height":120},"531ABF74CF7676897A7D78D5CAD13D8B":{"type":"texture","index":1,"url":{"native":"assets\/5BE811FD-EF1B-4AAF-A494-4BCAB0D96B98.pdf"},"width":1962,"height":1104},"422AB893ED376F577DF542C85A4279C1":{"type":"texture","index":8,"url":{"native":"assets\/5BE811FD-EF1B-4AAF-A494-4BCAB0D96B98.pdf"},"width":1920,"height":1080},"D3687024EA01E3D4A2FCA65042DFA5FD":{"type":"texture","index":9,"url":{"native":"assets\/5BE811FD-EF1B-4AAF-A494-4BCAB0D96B98.pdf"},"width":1920,"height":1080},"160C14F8F8B0D9F2E8FC7505D62CE3FA":{"type":"texture","index":7,"url":{"native":"assets\/5BE811FD-EF1B-4AAF-A494-4BCAB0D96B98.pdf"},"width":1961.509521484375,"height":1103.34912109375}},"events":[{"effects":[{"beginTime":0,"baseLayer":{"animations":[],"initialState":{"affineTransform":[1,0,0,1,0,0],"masksToBounds":false,"rotation":0,"scale":1,"position":{"pointX":960,"pointY":540.00002288818359},"width":1961.509521484375,"sublayerTransform":[1,0,0,0,0,1,0,0,0,0,1,0,0,0,0,1],"contentsRect":{"y":0,"x":0,"width":1,"height":1},"opacity":1,"edgeAntialiasingMask":251658240,"height":1103.34912109375,"hidden":false,"anchorPoint":{"pointX":0.5,"pointY":0.5}},"objectID":"52102042-CCAA-4687-8E8C-661C10898111","layers":[{"animations":[],"layers":[],"texturedRectangle":{"isBackgroundTexture":true,"singleTextureOpacity":1,"textureType":5,"textBaseline":0,"textXHeight":0,"isVerticalText":false},"initialState":{"affineTransform":[1,0,0,1,0,0],"masksToBounds":false,"rotation":0,"scale":1,"position":{"pointX":980.7547607421875,"pointY":551.67453765869141},"width":1962,"sublayerTransform":[1,0,0,0,0,1,0,0,0,0,1,0,0,0,0,1],"contentsRect":{"y":0,"x":0,"width":1,"height":1},"opacity":1,"edgeAntialiasingMask":0,"height":1104,"hidden":true,"anchorPoint":{"pointX":0.5,"pointY":0.5}},"texture":"531ABF74CF7676897A7D78D5CAD13D8B"},{"animations":[],"layers":[],"isVideoLayer":true,"initialState":{"affineTransform":[1,0,0,1,0,0],"masksToBounds":false,"rotation":0,"scale":1,"position":{"pointX":980.7547607421875,"pointY":551.674560546875},"width":1961.509521484375,"sublayerTransform":[1,0,0,0,0,1,0,0,0,0,1,0,0,0,0,1],"contentsRect":{"y":0,"x":0,"width":1,"height":1},"opacity":1,"edgeAntialiasingMask":251658240,"height":1103.34912109375,"hidden":false,"anchorPoint":{"pointX":0.5,"pointY":0.5}},"texture":"160C14F8F8B0D9F2E8FC7505D62CE3FA"}]},"effects":[],"movie":{"volume":1,"isStreaming":false,"isAudioOnly":false,"endTime":18.387666702270508,"startTime":0,"asset":"AdobeStock_266739495.mov-0.0000-18.3877","loopMode":"looping"},"duration":0,"type":"buildIn","attributes":{"direction":0},"name":"renderMovie","objectID":"52102042-CCAA-4687-8E8C-661C10898111"}],"automaticPlay":true,"hyperlinks":[],"accessibility":[{"text":"MENO_ORNAMENT.svg","targetRectangle":{"y":357,"x":-6.652923583984375,"width":75.383216857910156,"height":366}},{"text":"Click & collect, livraison rapide et outils numériques deviennent essentiels pour la compétitivité","targetRectangle":{"y":909.8305675983429,"x":658.6710205078125,"width":1233.4850000000001,"height":132}},{"text":"Bronnen:  6W Research, Retail Detail, ECDB","targetRectangle":{"y":42.818435430526733,"x":48.240986824035645,"width":447.35999999999984,"height":29}},{"text":"E-commerce & omnicanal","targetRectangle":{"y":915.13056683540344,"x":123.31179382324217,"width":393.08500000000004,"height":125.39999842643738}}],"baseLayer":{"animations":[],"initialState":{"affineTransform":[1,0,0,1,0,0],"masksToBounds":false,"rotation":0,"scale":1,"position":{"pointX":960,"pointY":540},"width":1920,"sublayerTransform":[1,0,0,0,0,1,0,0,0,0,1,0,0,0,0,1],"contentsRect":{"y":0,"x":0,"width":1,"height":1},"opacity":1,"edgeAntialiasingMask":251658240,"height":1080,"hidden":false,"anchorPoint":{"pointX":0.5,"pointY":0.5}},"layers":[{"animations":[],"initialState":{"affineTransform":[1,0,0,1,0,0],"masksToBounds":false,"rotation":0,"scale":1,"position":{"pointX":960,"pointY":540},"width":1920,"sublayerTransform":[1,0,0,0,0,1,0,0,0,0,1,0,0,0,0,1],"contentsRect":{"y":0,"x":0,"width":1,"height":1},"opacity":1,"edgeAntialiasingMask":251658240,"height":1080,"hidden":false,"anchorPoint":{"pointX":0.5,"pointY":0.5}},"layers":[{"animations":[],"initialState":{"affineTransform":[1,0,0,1,0,0],"masksToBounds":false,"rotation":0,"scale":1,"position":{"pointX":960,"pointY":540},"width":1920,"sublayerTransform":[1,0,0,0,0,1,0,0,0,0,1,0,0,0,0,1],"contentsRect":{"y":0,"x":0,"width":1,"height":1},"opacity":1,"edgeAntialiasingMask":251658240,"height":1080,"hidden":false,"anchorPoint":{"pointX":0.5,"pointY":0.5}},"layers":[{"animations":[],"layers":[],"texturedRectangle":{"isBackgroundTexture":true,"singleTextureOpacity":1,"textureType":1,"textBaseline":0,"textXHeight":0,"isVerticalText":false},"initialState":{"affineTransform":[1,0,0,1,0,0],"masksToBounds":false,"rotation":0,"scale":1,"position":{"pointX":960,"pointY":540},"width":1920,"sublayerTransform":[1,0,0,0,0,1,0,0,0,0,1,0,0,0,0,1],"contentsRect":{"y":0,"x":0,"width":1,"height":1},"opacity":1,"edgeAntialiasingMask":0,"height":1080,"hidden":false,"anchorPoint":{"pointX":0.5,"pointY":0.5}},"texture":"C25C25FF361FB24FC35F6B120D2F252D"}]}]},{"animations":[],"initialState":{"affineTransform":[1,0,0,1,0,0],"masksToBounds":false,"rotation":0,"scale":1,"position":{"pointX":960,"pointY":540},"width":1920,"sublayerTransform":[1,0,0,0,0,1,0,0,0,0,1,0,0,0,0,1],"contentsRect":{"y":0,"x":0,"width":1,"height":1},"opacity":1,"edgeAntialiasingMask":251658240,"height":1080,"hidden":false,"anchorPoint":{"pointX":0.5,"pointY":0.5}},"layers":[{"animations":[],"initialState":{"affineTransform":[1,0,0,1,0,0],"masksToBounds":false,"rotation":0,"scale":1,"position":{"pointX":960,"pointY":540.00002288818359},"width":1961.509521484375,"sublayerTransform":[1,0,0,0,0,1,0,0,0,0,1,0,0,0,0,1],"contentsRect":{"y":0,"x":0,"width":1,"height":1},"opacity":1,"edgeAntialiasingMask":251658240,"height":1103.34912109375,"hidden":false,"anchorPoint":{"pointX":0.5,"pointY":0.5}},"objectID":"52102042-CCAA-4687-8E8C-661C10898111","layers":[{"animations":[],"layers":[],"texturedRectangle":{"isBackgroundTexture":true,"singleTextureOpacity":1,"textureType":5,"textBaseline":0,"textXHeight":0,"isVerticalText":false},"initialState":{"affineTransform":[1,0,0,1,0,0],"masksToBounds":false,"rotation":0,"scale":1,"position":{"pointX":980.7547607421875,"pointY":551.67453765869141},"width":1962,"sublayerTransform":[1,0,0,0,0,1,0,0,0,0,1,0,0,0,0,1],"contentsRect":{"y":0,"x":0,"width":1,"height":1},"opacity":1,"edgeAntialiasingMask":0,"height":1104,"hidden":false,"anchorPoint":{"pointX":0.5,"pointY":0.5}},"texture":"531ABF74CF7676897A7D78D5CAD13D8B"}]}]},{"animations":[],"initialState":{"affineTransform":[1,0,0,1,0,0],"masksToBounds":false,"rotation":0,"scale":1,"position":{"pointX":960,"pointY":540},"width":1920,"sublayerTransform":[1,0,0,0,0,1,0,0,0,0,1,0,0,0,0,1],"contentsRect":{"y":0,"x":0,"width":1,"height":1},"opacity":1,"edgeAntialiasingMask":251658240,"height":1080,"hidden":false,"anchorPoint":{"pointX":0.5,"pointY":0.5}},"layers":[{"animations":[],"initialState":{"affineTransform":[1,0,0,1,0,0],"masksToBounds":false,"rotation":0,"scale":1,"position":{"pointX":32.347076416015625,"pointY":541},"width":78,"sublayerTransform":[1,0,0,0,0,1,0,0,0,0,1,0,0,0,0,1],"contentsRect":{"y":0,"x":0,"width":1,"height":1},"opacity":1,"edgeAntialiasingMask":251658240,"height":368,"hidden":false,"anchorPoint":{"pointX":0.5,"pointY":0.5}},"layers":[{"animations":[],"layers":[],"texturedRectangle":{"isBackgroundTexture":true,"singleTextureOpacity":1,"textureType":5,"textBaseline":0,"textXHeight":0,"isVerticalText":false},"initialState":{"affineTransform":[1,0,0,1,0,0],"masksToBounds":false,"rotation":0,"scale":1,"position":{"pointX":37.652923583984375,"pointY":183},"width":78,"sublayerTransform":[1,0,0,0,0,1,0,0,0,0,1,0,0,0,0,1],"contentsRect":{"y":0,"x":0,"width":1,"height":1},"opacity":1,"edgeAntialiasingMask":0,"height":368,"hidden":false,"anchorPoint":{"pointX":0.5,"pointY":0.5}},"texture":"5E5E1E95F6034F4F396B66AE5DC1F5A8"}]}]},{"animations":[],"initialState":{"affineTransform":[1,0,0,1,0,0],"masksToBounds":false,"rotation":0,"scale":1,"position":{"pointX":960,"pointY":540},"width":1920,"sublayerTransform":[1,0,0,0,0,1,0,0,0,0,1,0,0,0,0,1],"contentsRect":{"y":0,"x":0,"width":1,"height":1},"opacity":1,"edgeAntialiasingMask":251658240,"height":1080,"hidden":false,"anchorPoint":{"pointX":0.5,"pointY":0.5}},"layers":[{"animations":[],"initialState":{"affineTransform":[1,0,0,1,0,0],"masksToBounds":false,"rotation":0,"scale":1,"position":{"pointX":966.4592502117157,"pointY":942.4462890625},"width":1936,"sublayerTransform":[1,0,0,0,0,1,0,0,0,0,1,0,0,0,0,1],"contentsRect":{"y":0,"x":0,"width":1,"height":1},"opacity":1,"edgeAntialiasingMask":251658240,"height":295,"hidden":false,"anchorPoint":{"pointX":0.5,"pointY":0.5}},"layers":[{"animations":[],"layers":[],"texturedRectangle":{"singleTextureOpacity":1,"textXHeight":0,"shapePath":{"lineWidth":1,"flatness":0.59999999999999998,"lineCapStyle":0,"elements":[{"type":"MoveToPoint","points":[[1.4592502117156982,1.9462890625]]},{"type":"AddLine","points":[[1934.1678683757782,1.9462890625]]},{"type":"AddLine","points":[[1934.1678683757782,293.53192138671875]]},{"type":"AddLine","points":[[1.4592502117156982,293.53192138671875]]},{"type":"CloseSubpath"},{"type":"MoveToPoint","points":[[1.4592502117156982,1.9462890625]]}],"windingRule":0,"lineJoinStyle":0,"miterLimit":10},"isBackgroundTexture":true,"textBaseline":0,"isVerticalText":false,"textureType":5},"initialState":{"affineTransform":[1,0,0,1,0,0],"masksToBounds":false,"rotation":0,"scale":1,"position":{"pointX":966.5407497882843,"pointY":145.5537109375},"width":1936,"sublayerTransform":[1,0,0,0,0,1,0,0,0,0,1,0,0,0,0,1],"contentsRect":{"y":0,"x":0,"width":1,"height":1},"opacity":1,"edgeAntialiasingMask":0,"height":295,"hidden":false,"anchorPoint":{"pointX":0.5,"pointY":0.5}},"texture":"05FF591A24F0531751D2F3C5FC5C4823"}]}]},{"animations":[],"initialState":{"affineTransform":[1,0,0,1,0,0],"masksToBounds":false,"rotation":0,"scale":1,"position":{"pointX":960,"pointY":540},"width":1920,"sublayerTransform":[1,0,0,0,0,1,0,0,0,0,1,0,0,0,0,1],"contentsRect":{"y":0,"x":0,"width":1,"height":1},"opacity":1,"edgeAntialiasingMask":251658240,"height":1080,"hidden":false,"anchorPoint":{"pointX":0.5,"pointY":0.5}},"layers":[{"animations":[],"initialState":{"affineTransform":[1,0,0,1,0,0],"masksToBounds":false,"rotation":0,"scale":1,"position":{"pointX":267.58859252929688,"pointY":962.63056683540344},"width":382,"sublayerTransform":[1,0,0,0,0,1,0,0,0,0,1,0,0,0,0,1],"contentsRect":{"y":0,"x":0,"width":1,"height":1},"opacity":1,"edgeAntialiasingMask":251658240,"height":103,"hidden":false,"anchorPoint":{"pointX":0.5,"pointY":0.5}},"layers":[{"animations":[],"layers":[],"texturedRectangle":{"singleTextureOpacity":1,"textXHeight":0.27446601941747573,"textBaseline":0.96631779717010202,"isBackgroundTexture":true,"isVerticalText":false,"textColor":[0.99991613626480103,1,0.99988490343093872,1],"textureType":6},"initialState":{"affineTransform":[1,0,0,1,0,0],"masksToBounds":false,"rotation":0,"scale":1,"position":{"pointX":239.41140747070312,"pointY":70.369433164596558},"width":382,"sublayerTransform":[1,0,0,0,0,1,0,0,0,0,1,0,0,0,0,1],"contentsRect":{"y":0,"x":0,"width":1,"height":1},"opacity":1,"edgeAntialiasingMask":0,"height":103,"hidden":false,"anchorPoint":{"pointX":0.5,"pointY":0.5}},"texture":"0B143BA6911C8E83FB8E8707BC7A323C"}]}]},{"animations":[],"initialState":{"affineTransform":[1,0,0,1,0,0],"masksToBounds":false,"rotation":0,"scale":1,"position":{"pointX":960,"pointY":540},"width":1920,"sublayerTransform":[1,0,0,0,0,1,0,0,0,0,1,0,0,0,0,1],"contentsRect":{"y":0,"x":0,"width":1,"height":1},"opacity":1,"edgeAntialiasingMask":251658240,"height":1080,"hidden":false,"anchorPoint":{"pointX":0.5,"pointY":0.5}},"layers":[{"animations":[],"initialState":{"affineTransform":[1,0,0,1,0,0],"masksToBounds":false,"rotation":0,"scale":1,"position":{"pointX":1266.1710205078125,"pointY":965.8305675983429},"width":1223,"sublayerTransform":[1,0,0,0,0,1,0,0,0,0,1,0,0,0,0,1],"contentsRect":{"y":0,"x":0,"width":1,"height":1},"opacity":1,"edgeAntialiasingMask":251658240,"height":120,"hidden":false,"anchorPoint":{"pointX":0.5,"pointY":0.5}},"layers":[{"animations":[],"layers":[],"texturedRectangle":{"singleTextureOpacity":1,"textXHeight":0.23191666666666669,"textBaseline":0.89858946204185486,"isBackgroundTexture":true,"isVerticalText":false,"textColor":[0.99991613626480103,1,0.99988490343093872,1],"textureType":6},"initialState":{"affineTransform":[1,0,0,1,0,0],"masksToBounds":false,"rotation":0,"scale":1,"position":{"pointX":616.8289794921875,"pointY":77.169432401657104},"width":1223,"sublayerTransform":[1,0,0,0,0,1,0,0,0,0,1,0,0,0,0,1],"contentsRect":{"y":0,"x":0,"width":1,"height":1},"opacity":1,"edgeAntialiasingMask":0,"height":120,"hidden":false,"anchorPoint":{"pointX":0.5,"pointY":0.5}},"texture":"0FE07C9B32DA6205569FAD6450FF1E81"}]}]},{"animations":[],"initialState":{"affineTransform":[1,0,0,1,0,0],"masksToBounds":false,"rotation":0,"scale":1,"position":{"pointX":960,"pointY":540},"width":1920,"sublayerTransform":[1,0,0,0,0,1,0,0,0,0,1,0,0,0,0,1],"contentsRect":{"y":0,"x":0,"width":1,"height":1},"opacity":1,"edgeAntialiasingMask":251658240,"height":1080,"hidden":false,"anchorPoint":{"pointX":0.5,"pointY":0.5}},"layers":[{"animations":[],"initialState":{"affineTransform":[1,0,0,1,0,0],"masksToBounds":false,"rotation":0,"scale":1,"position":{"pointX":267.74098682403564,"pointY":50.318435430526733},"width":448,"sublayerTransform":[1,0,0,0,0,1,0,0,0,0,1,0,0,0,0,1],"contentsRect":{"y":0,"x":0,"width":1,"height":1},"opacity":1,"edgeAntialiasingMask":251658240,"height":23,"hidden":false,"anchorPoint":{"pointX":0.5,"pointY":0.5}},"layers":[{"animations":[],"layers":[],"texturedRectangle":{"singleTextureOpacity":1,"textXHeight":0.52800000000000002,"textBaseline":0.82689168142235803,"isBackgroundTexture":true,"isVerticalText":false,"textColor":[0,0,0,1],"textureType":6},"initialState":{"affineTransform":[1,0,0,1,0,0],"masksToBounds":false,"rotation":0,"scale":1,"position":{"pointX":228.25901317596436,"pointY":20.681564569473267},"width":448,"sublayerTransform":[1,0,0,0,0,1,0,0,0,0,1,0,0,0,0,1],"contentsRect":{"y":0,"x":0,"width":1,"height":1},"opacity":1,"edgeAntialiasingMask":0,"height":23,"hidden":false,"anchorPoint":{"pointX":0.5,"pointY":0.5}},"texture":"4DCB6BA1E98373574D43AEEA1A1006BB"}]}]}]}},{"effects":[{"beginTime":0,"baseLayer":{"animations":[],"initialState":{"affineTransform":[1,0,0,1,0,0],"masksToBounds":false,"rotation":0,"scale":1,"position":{"pointX":960,"pointY":540},"width":1920,"sublayerTransform":[1,0,0,0,0,1,0,0,0,0,1,0,0,0,0,1],"contentsRect":{"y":0,"x":0,"width":1,"height":1},"opacity":1,"edgeAntialiasingMask":251658240,"height":1080,"hidden":false,"anchorPoint":{"pointX":0.5,"pointY":0.5}},"objectID":"0","layers":[{"animations":[],"initialState":{"affineTransform":[1,0,0,1,0,0],"masksToBounds":false,"rotation":0,"scale":1,"position":{"pointX":960,"pointY":540},"width":1920,"sublayerTransform":[1,0,0,0,0,1,0,0,0,0,1,-0.00035007912466775983,0,0,0,1],"contentsRect":{"y":0,"x":0,"width":1,"height":1},"opacity":1,"edgeAntialiasingMask":251658240,"height":1080,"hidden":false,"anchorPoint":{"pointX":0.5,"pointY":0.5}},"layers":[{"animations":[],"layers":[],"texturedRectangle":{"isBackgroundTexture":false,"singleTextureOpacity":1,"textureType":0,"textBaseline":0,"textXHeight":0,"isVerticalText":false},"initialState":{"affineTransform":[1,0,0,1,0,0],"masksToBounds":false,"rotation":0,"scale":1,"position":{"pointX":960,"pointY":540},"width":1920,"sublayerTransform":[1,0,0,0,0,1,0,0,0,0,1,0,0,0,0,1],"contentsRect":{"y":0,"x":0,"width":1,"height":1},"opacity":1,"edgeAntialiasingMask":0,"height":1080,"hidden":false,"anchorPoint":{"pointX":0.5,"pointY":0.5}},"texture":"D3687024EA01E3D4A2FCA65042DFA5FD"},{"animations":[{"additive":false,"timeOffset":0,"beginTime":0,"from":{"scalar":false},"repeatCount":0,"fillMode":"both","duration":0.001,"autoreverses":false,"property":"hidden","to":{"scalar":true},"removedOnCompletion":false}],"layers":[],"texturedRectangle":{"isBackgroundTexture":false,"singleTextureOpacity":1,"textureType":0,"textBaseline":0,"textXHeight":0,"isVerticalText":false},"initialState":{"affineTransform":[1,0,0,1,0,0],"masksToBounds":false,"rotation":0,"scale":1,"position":{"pointX":960,"pointY":540},"width":1920,"sublayerTransform":[1,0,0,0,0,1,0,0,0,0,1,0,0,0,0,1],"contentsRect":{"y":0,"x":0,"width":1,"height":1},"opacity":1,"edgeAntialiasingMask":0,"height":1080,"hidden":false,"anchorPoint":{"pointX":0.5,"pointY":0.5}},"texture":"422AB893ED376F577DF542C85A4279C1"}]}]},"effects":[],"duration":0.001,"type":"transition","attributes":{"direction":0},"name":"none","objectID":"0"}],"automaticPlay":false,"hyperlinks":[],"accessibility":[{"text":"MENO_ORNAMENT.svg","targetRectangle":{"y":357,"x":-6.652923583984375,"width":75.383216857910156,"height":366}},{"text":"Click & collect, livraison rapide et outils numériques deviennent essentiels pour la compétitivité","targetRectangle":{"y":909.8305675983429,"x":658.6710205078125,"width":1233.4850000000001,"height":132}},{"text":"AdobeStock_266739495.mov","targetRectangle":{"y":-11.674537658691406,"x":-20.7547607421875,"width":1961.509521484375,"height":1103.34912109375}},{"text":"Bronnen:  6W Research, Retail Detail, ECDB","targetRectangle":{"y":42.818435430526733,"x":48.240986824035645,"width":447.35999999999984,"height":29}},{"text":"E-commerce & omnicanal","targetRectangle":{"y":915.13056683540344,"x":123.31179382324217,"width":393.08500000000004,"height":125.39999842643738}}],"baseLayer":{"animations":[],"initialState":{"affineTransform":[1,0,0,1,0,0],"masksToBounds":false,"rotation":0,"scale":1,"position":{"pointX":960,"pointY":540},"width":1920,"sublayerTransform":[1,0,0,0,0,1,0,0,0,0,1,0,0,0,0,1],"contentsRect":{"y":0,"x":0,"width":1,"height":1},"opacity":1,"edgeAntialiasingMask":251658240,"height":1080,"hidden":false,"anchorPoint":{"pointX":0.5,"pointY":0.5}},"objectID":"0","layers":[{"animations":[],"initialState":{"affineTransform":[1,0,0,1,0,0],"masksToBounds":false,"rotation":0,"scale":1,"position":{"pointX":960,"pointY":540},"width":1920,"sublayerTransform":[1,0,0,0,0,1,0,0,0,0,1,-0.00035007912466775983,0,0,0,1],"contentsRect":{"y":0,"x":0,"width":1,"height":1},"opacity":1,"edgeAntialiasingMask":251658240,"height":1080,"hidden":false,"anchorPoint":{"pointX":0.5,"pointY":0.5}},"layers":[{"animations":[],"layers":[],"texturedRectangle":{"isBackgroundTexture":false,"singleTextureOpacity":1,"textureType":0,"textBaseline":0,"textXHeight":0,"isVerticalText":false},"initialState":{"affineTransform":[1,0,0,1,0,0],"masksToBounds":false,"rotation":0,"scale":1,"position":{"pointX":960,"pointY":540},"width":1920,"sublayerTransform":[1,0,0,0,0,1,0,0,0,0,1,0,0,0,0,1],"contentsRect":{"y":0,"x":0,"width":1,"height":1},"opacity":1,"edgeAntialiasingMask":0,"height":1080,"hidden":false,"anchorPoint":{"pointX":0.5,"pointY":0.5}},"texture":"422AB893ED376F577DF542C85A4279C1"}]}]}}]}